README.md
setup.py
gram/__init__.py
gram/__main__.py
gram/gram.py
gram.egg-info/PKG-INFO
gram.egg-info/SOURCES.txt
gram.egg-info/dependency_links.txt
gram.egg-info/entry_points.txt
gram.egg-info/requires.txt
gram.egg-info/top_level.txt