Metadata-Version: 1.0
Name: gram
Version: 0.1.0
Summary: gram: GitHub Repo Account Manager
Home-page: UNKNOWN
Author: Lily Mayfield
Author-email: lily.m.mayfield@gmail.com
License: UNKNOWN
Keywords: cli
Platform: UNKNOWN
